pyurlextract/__init__.py
pyurlextract/expander.py
pyurlextract-1.1.dist-info/LICENSE
pyurlextract-1.1.dist-info/METADATA
pyurlextract-1.1.dist-info/WHEEL
pyurlextract-1.1.dist-info/top_level.txt
pyurlextract-1.1.dist-info/RECORD
